{
    "marks" : [
               {
               "link" : "http://www.framebridge.com",
               "time" : 0,
               "imageLocation" : "framebridge"
               },
               {
               "link" : "https://instagram.com/shirley_braha/",
               "time" : 23,
               "imageLocation" : "shirleyBraha"
               },
               {
               "link" : "https://instagram.com/marniethedog/",
               "time" : 101,
               "imageLocation" : "marnie"
               },
               {
               "link" : "https://vine.co/v/OZQ61X9KWwB",
               "time" : 170,
               "imageLocation" : "marniePharmacy"
               }, 
               {
               "link" : "http://www.replyall.limo",
               "time" : 198,
               "imageLocation" : "replyAllLogo"
               }
               ]
}